Pyvyctor/GeneralizedVector.py
Pyvyctor/ObjectVector.py
Pyvyctor/__init__.py
Pyvyctor/vector2d.py
Pyvyctor/vector3d.py
Pyvyctor-1.0.1.dist-info/METADATA
Pyvyctor-1.0.1.dist-info/WHEEL
Pyvyctor-1.0.1.dist-info/top_level.txt
Pyvyctor-1.0.1.dist-info/RECORD
