Metadata-Version: 2.1
Name: Pyvyctor
Version: 1.0.1
Summary: A small python module implementing 2d and 3d vectors only
Home-page: UNKNOWN
Author: Didictateur
Author-email: decosse.adrien@gmail.com
License: UNKNOWN
Platform: UNKNOWN
